morph_gen/__init__.py
morph_gen/ch.csv
morph_gen/change.csv
morph_gen/dictionary.txt
morph_gen/example.csv
morph_gen/nounsuf.txt
morph_gen/suffixdvithva.txt
morph_gen/suffixmorph.txt
morph_gen/suffverb.txt
morph_gen/verb.txt
morph_gen/verbsuf.txt
morph_gen-1.1.1.dist-info/LICENSE.txt
morph_gen-1.1.1.dist-info/METADATA
morph_gen-1.1.1.dist-info/WHEEL
morph_gen-1.1.1.dist-info/top_level.txt
morph_gen-1.1.1.dist-info/RECORD
