Metadata-Version: 2.1
Name: morph-gen
Version: 1.1.1
Summary: Extract a list with stem and stripped suffixes from a Malayalam word
Home-page: https://gitlab.com/icfoss/Malayalam-Computing/Morpheme_Generator_for_Malayalam
Author: Jincy Baby
Author-email: jincybaby@icfoss.org
License: GNU Public License
Platform: UNKNOWN
Classifier: Programming Language :: Python :: 3
Classifier: Operating System :: OS Independent
